[
  {
    "filename": "barrel1.png",
    "name": "barrel1"
  },
  {
    "filename": "campfire1.png",
    "name": "campfire1"
  },
  {
    "filename": "chest1.png",
    "name": "chest1"
  },
  {
    "filename": "fence1.png",
    "name": "fence1"
  },
  {
    "filename": "fence2.png",
    "name": "fence2"
  },
  {
    "filename": "flowers1.png",
    "name": "flowers1"
  },
  {
    "filename": "flowers2.png",
    "name": "flowers2"
  },
  {
    "filename": "flowers3.png",
    "name": "flowers3"
  },
  {
    "filename": "flowers4.png",
    "name": "flowers4"
  },
  {
    "filename": "hut1.png",
    "name": "hut1"
  },
  {
    "filename": "hut2.png",
    "name": "hut2"
  },
  {
    "filename": "hut3.png",
    "name": "hut3"
  },
  {
    "filename": "leaves1.png",
    "name": "leaves1"
  },
  {
    "filename": "leaves2.png",
    "name": "leaves2"
  },
  {
    "filename": "leaves3.png",
    "name": "leaves3"
  },
  {
    "filename": "logs1.png",
    "name": "logs1"
  },
  {
    "filename": "mound1.png",
    "name": "mound1"
  },
  {
    "filename": "mound2.png",
    "name": "mound2"
  },
  {
    "filename": "mound3.png",
    "name": "mound3"
  },
  {
    "filename": "mound4.png",
    "name": "mound4"
  },
  {
    "filename": "mound5.png",
    "name": "mound5"
  },
  {
    "filename": "mound6.png",
    "name": "mound6"
  },
  {
    "filename": "plant1.png",
    "name": "plant1"
  },
  {
    "filename": "plant2.png",
    "name": "plant2"
  },
  {
    "filename": "plant3.png",
    "name": "plant3"
  },
  {
    "filename": "plant4.png",
    "name": "plant4"
  },
  {
    "filename": "plant5.png",
    "name": "plant5"
  },
  {
    "filename": "screen1.png",
    "name": "screen1"
  },
  {
    "filename": "scroll1.png",
    "name": "scroll1"
  },
  {
    "filename": "stone1.png",
    "name": "stone1"
  },
  {
    "filename": "stone2.png",
    "name": "stone2"
  },
  {
    "filename": "stone3.png",
    "name": "stone3"
  },
  {
    "filename": "stone4.png",
    "name": "stone4"
  },
  {
    "filename": "stone5.png",
    "name": "stone5"
  },
  {
    "filename": "table1.png",
    "name": "table1"
  },
  {
    "filename": "texture-grass.png",
    "name": "texture grass"
  },
  {
    "filename": "texture-sand.png",
    "name": "texture sand"
  },
  {
    "filename": "texture-water.png",
    "name": "texture water"
  },
  {
    "filename": "torch1.png",
    "name": "torch1"
  },
  {
    "filename": "tree1.png",
    "name": "tree1"
  },
  {
    "filename": "tree2.png",
    "name": "tree2"
  },
  {
    "filename": "tree3.png",
    "name": "tree3"
  },
  {
    "filename": "tree4.png",
    "name": "tree4"
  },
  {
    "filename": "water-barrel1.png",
    "name": "water barrel1"
  },
  {
    "filename": "water-branch1.png",
    "name": "water branch1"
  },
  {
    "filename": "water-plant1.png",
    "name": "water plant1"
  },
  {
    "filename": "water-plant2.png",
    "name": "water plant2"
  },
  {
    "filename": "water-plant3.png",
    "name": "water plant3"
  },
  {
    "filename": "water-rock1.png",
    "name": "water rock1"
  },
  {
    "filename": "water-rock2.png",
    "name": "water rock2"
  },
  {
    "filename": "water-rock3.png",
    "name": "water rock3"
  }
]
